data/__init__.py
data/cpp_template.txt
data/cpp_template_info.txt
data/data.py
data/get_template.py
data/py_template.txt
data/py_template_info.txt
run/__init__.py
run/cp_run.py
run/startup.py
settings/__init__.py
settings/bot.json
settings/compiler.py
settings/config.py
settings/default.conf
settings/first_load.py
settings/logs.py
settings/settings.conf
settings/settings.py
system/__about__.py
system/__init__.py
system/features_installation.py
system/get_time.py
system/install.py
system/internet.py
system/path.py
system/platform.py
system/screen_text.py
tools/ConfigParser.py
tools/__init__.py
tools/json_manager.py
tools/run_program.py
tools/OJ/__init__.py
tools/OJ/client.py
tools/OJ/cp.py
tools/OJ/socket_manager.py
tools/OJ/testing.py
tools/OJ/CP/__init__.py
tools/OJ/CP/add_test.py
tools/OJ/CP/bruteforce.py
tools/OJ/CP/contest.py
tools/OJ/CP/extension.py
tools/OJ/CP/help.py
tools/OJ/CP/login.py
tools/OJ/CP/problem.py
tools/OJ/CP/setup.py
tools/OJ/CP/submit.py
tools/OJ/CP/table.py
tools/OJ/CP/test.py
tools/OJ/CP/url_manager.py
cp_assistant-1.0.4.dist-info/LICENSE.txt
cp_assistant-1.0.4.dist-info/METADATA
cp_assistant-1.0.4.dist-info/WHEEL
cp_assistant-1.0.4.dist-info/entry_points.txt
cp_assistant-1.0.4.dist-info/top_level.txt
cp_assistant-1.0.4.dist-info/RECORD
